klip_nav/__init__.py
klip_nav/main.py
klip_nav/tui.py
klip_nav/utils.py
klip_nav-0.0.5.dist-info/METADATA
klip_nav-0.0.5.dist-info/WHEEL
klip_nav-0.0.5.dist-info/entry_points.txt
klip_nav-0.0.5.dist-info/licenses/LICENCE
klip_nav-0.0.5.dist-info/RECORD
