Metadata-Version: 2.1
Name: klip_nav
Version: 0.0.5
Summary: Python TUI for navigating kindle clippings
Project-URL: Homepage, https://github.com/skogsgren/klip-nav
Project-URL: Bug Tracker, https://github.com/skogsgren/klip-nav/issues
Author-email: skogsgren <6107181+skogsgren@users.noreply.github.com>
License-File: LICENCE
Classifier: License :: OSI Approved :: MIT License
Classifier: Operating System :: OS Independent
Classifier: Programming Language :: Python :: 3
Requires-Python: >=3.9
Requires-Dist: clipboard~=0.0.4
Requires-Dist: urwid~=2.1.2
Provides-Extra: test
Requires-Dist: coverage[toml]~=7.1; extra == 'test'
Requires-Dist: pytest-cov~=4.0; extra == 'test'
Requires-Dist: pytest~=7.2; extra == 'test'
